flight_routes
