Metadata-Version: 2.1
Name: flight-routes
Version: 0.0.5
Summary: kiwi 2021 entry task about flight route
Home-page: UNKNOWN
Author: Bc. Filip Agh
Author-email: filip11agh@gmail.com
License: UNKNOWN
Platform: UNKNOWN
Classifier: Programming Language :: Python :: 3.9
Classifier: License :: OSI Approved :: MIT License
Classifier: Operating System :: OS Independent
Requires-Python: >=3.9
License-File: LICENSE
